{"nodes": [{"id": "laundroapp", "label": "LaundroApp.tsx", "file_type": "code", "source_file": "components/LaundroApp.tsx", "source_location": "L1"}, {"id": "laundroapp_defaultvendorprofilefor", "label": "defaultVendorProfileFor()", "file_type": "code", "source_file": "components/LaundroApp.tsx", "source_location": "L197"}, {"id": "laundroapp_rowtouser", "label": "rowToUser()", "file_type": "code", "source_file": "components/LaundroApp.tsx", "source_location": "L211"}, {"id": "laundroapp_iscampuscollegestudent", "label": "isCampusCollegeStudent()", "file_type": "code", "source_file": "components/LaundroApp.tsx", "source_location": "L231"}, {"id": "laundroapp_needsstudentcollegechoice", "label": "needsStudentCollegeChoice()", "file_type": "code", "source_file": "components/LaundroApp.tsx", "source_location": "L238"}, {"id": "laundroapp_needsstudenthosteldetails", "label": "needsStudentHostelDetails()", "file_type": "code", "source_file": "components/LaundroApp.tsx", "source_location": "L245"}, {"id": "laundroapp_rowtoorder", "label": "rowToOrder()", "file_type": "code", "source_file": "components/LaundroApp.tsx", "source_location": "L254"}, {"id": "laundroapp_formatscheduleday", "label": "formatScheduleDay()", "file_type": "code", "source_file": "components/LaundroApp.tsx", "source_location": "L276"}, {"id": "laundroapp_validateindianphone", "label": "validateIndianPhone()", "file_type": "code", "source_file": "components/LaundroApp.tsx", "source_location": "L291"}, {"id": "laundroapp_tryapplysession", "label": "tryApplySession()", "file_type": "code", "source_file": "components/LaundroApp.tsx", "source_location": "L633"}, {"id": "laundroapp_init", "label": "init()", "file_type": "code", "source_file": "components/LaundroApp.tsx", "source_location": "L671"}, {"id": "laundroapp_refreshschedule", "label": "refreshSchedule()", "file_type": "code", "source_file": "components/LaundroApp.tsx", "source_location": "L760"}, {"id": "laundroapp_onfocus", "label": "onFocus()", "file_type": "code", "source_file": "components/LaundroApp.tsx", "source_location": "L767"}, {"id": "laundroapp_handleobnext", "label": "handleObNext()", "file_type": "code", "source_file": "components/LaundroApp.tsx", "source_location": "L949"}, {"id": "laundroapp_handleobskip", "label": "handleObSkip()", "file_type": "code", "source_file": "components/LaundroApp.tsx", "source_location": "L956"}, {"id": "laundroapp_handleloginemail", "label": "handleLoginEmail()", "file_type": "code", "source_file": "components/LaundroApp.tsx", "source_location": "L961"}, {"id": "laundroapp_handlegooglelogin", "label": "handleGoogleLogin()", "file_type": "code", "source_file": "components/LaundroApp.tsx", "source_location": "L999"}, {"id": "laundroapp_handleforgotpassword", "label": "handleForgotPassword()", "file_type": "code", "source_file": "components/LaundroApp.tsx", "source_location": "L1008"}, {"id": "laundroapp_handlesetpassword", "label": "handleSetPassword()", "file_type": "code", "source_file": "components/LaundroApp.tsx", "source_location": "L1030"}, {"id": "laundroapp_handlesavestudentdetailsmodal", "label": "handleSaveStudentDetailsModal()", "file_type": "code", "source_file": "components/LaundroApp.tsx", "source_location": "L1084"}, {"id": "laundroapp_handlesignup", "label": "handleSignup()", "file_type": "code", "source_file": "components/LaundroApp.tsx", "source_location": "L1131"}, {"id": "laundroapp_handlecompleteprofile", "label": "handleCompleteProfile()", "file_type": "code", "source_file": "components/LaundroApp.tsx", "source_location": "L1200"}, {"id": "laundroapp_handlesaveeditprofile", "label": "handleSaveEditProfile()", "file_type": "code", "source_file": "components/LaundroApp.tsx", "source_location": "L1252"}, {"id": "laundroapp_handleselectvendor", "label": "handleSelectVendor()", "file_type": "code", "source_file": "components/LaundroApp.tsx", "source_location": "L1305"}, {"id": "laundroapp_handlescheduleservice", "label": "handleScheduleService()", "file_type": "code", "source_file": "components/LaundroApp.tsx", "source_location": "L1309"}, {"id": "laundroapp_handlescheduledateslot", "label": "handleScheduleDateSlot()", "file_type": "code", "source_file": "components/LaundroApp.tsx", "source_location": "L1313"}, {"id": "laundroapp_handleconfirmorder", "label": "handleConfirmOrder()", "file_type": "code", "source_file": "components/LaundroApp.tsx", "source_location": "L1317"}, {"id": "laundroapp_handleconfirmdelivery", "label": "handleConfirmDelivery()", "file_type": "code", "source_file": "components/LaundroApp.tsx", "source_location": "L1400"}, {"id": "laundroapp_handlelogout", "label": "handleLogout()", "file_type": "code", "source_file": "components/LaundroApp.tsx", "source_location": "L1420"}, {"id": "laundroapp_handlesetpasswordforemail", "label": "handleSetPasswordForEmail()", "file_type": "code", "source_file": "components/LaundroApp.tsx", "source_location": "L1430"}, {"id": "laundroapp_mybillsloading", "label": "myBillsLoading()", "file_type": "code", "source_file": "components/LaundroApp.tsx", "source_location": "L2447"}], "edges": [{"source": "laundroapp", "target": "react", "relation": "imports_from", "confidence": "EXTRACTED", "source_file": "components/LaundroApp.tsx", "source_location": "L3", "weight": 1.0}, {"source": "laundroapp", "target": "link", "relation": "imports_from", "confidence": "EXTRACTED", "source_file": "components/LaundroApp.tsx", "source_location": "L4", "weight": 1.0}, {"source": "laundroapp", "target": "lucide_react", "relation": "imports_from", "confidence": "EXTRACTED", "source_file": "components/LaundroApp.tsx", "source_location": "L5", "weight": 1.0}, {"source": "laundroapp", "target": "swipetoconfirm", "relation": "imports_from", "confidence": "EXTRACTED", "source_file": "components/LaundroApp.tsx", "source_location": "L6", "weight": 1.0}, {"source": "laundroapp", "target": "turnstilewidget", "relation": "imports_from", "confidence": "EXTRACTED", "source_file": "components/LaundroApp.tsx", "source_location": "L7", "weight": 1.0}, {"source": "laundroapp", "target": "constants", "relation": "imports_from", "confidence": "EXTRACTED", "source_file": "components/LaundroApp.tsx", "source_location": "L8", "weight": 1.0}, {"source": "laundroapp", "target": "api", "relation": "imports_from", "confidence": "EXTRACTED", "source_file": "components/LaundroApp.tsx", "source_location": "L17", "weight": 1.0}, {"source": "laundroapp", "target": "api", "relation": "imports_from", "confidence": "EXTRACTED", "source_file": "components/LaundroApp.tsx", "source_location": "L18", "weight": 1.0}, {"source": "laundroapp", "target": "api", "relation": "imports_from", "confidence": "EXTRACTED", "source_file": "components/LaundroApp.tsx", "source_location": "L19", "weight": 1.0}, {"source": "laundroapp", "target": "terms", "relation": "imports_from", "confidence": "EXTRACTED", "source_file": "components/LaundroApp.tsx", "source_location": "L20", "weight": 1.0}, {"source": "laundroapp", "target": "fees", "relation": "imports_from", "confidence": "EXTRACTED", "source_file": "components/LaundroApp.tsx", "source_location": "L21", "weight": 1.0}, {"source": "laundroapp", "target": "laundroapp_defaultvendorprofilefor", "relation": "contains", "confidence": "EXTRACTED", "source_file": "components/LaundroApp.tsx", "source_location": "L197", "weight": 1.0}, {"source": "laundroapp", "target": "laundroapp_rowtouser", "relation": "contains", "confidence": "EXTRACTED", "source_file": "components/LaundroApp.tsx", "source_location": "L211", "weight": 1.0}, {"source": "laundroapp", "target": "laundroapp_iscampuscollegestudent", "relation": "contains", "confidence": "EXTRACTED", "source_file": "components/LaundroApp.tsx", "source_location": "L231", "weight": 1.0}, {"source": "laundroapp", "target": "laundroapp_needsstudentcollegechoice", "relation": "contains", "confidence": "EXTRACTED", "source_file": "components/LaundroApp.tsx", "source_location": "L238", "weight": 1.0}, {"source": "laundroapp", "target": "laundroapp_needsstudenthosteldetails", "relation": "contains", "confidence": "EXTRACTED", "source_file": "components/LaundroApp.tsx", "source_location": "L245", "weight": 1.0}, {"source": "laundroapp", "target": "laundroapp_rowtoorder", "relation": "contains", "confidence": "EXTRACTED", "source_file": "components/LaundroApp.tsx", "source_location": "L254", "weight": 1.0}, {"source": "laundroapp", "target": "laundroapp_formatscheduleday", "relation": "contains", "confidence": "EXTRACTED", "source_file": "components/LaundroApp.tsx", "source_location": "L276", "weight": 1.0}, {"source": "laundroapp", "target": "laundroapp_validateindianphone", "relation": "contains", "confidence": "EXTRACTED", "source_file": "components/LaundroApp.tsx", "source_location": "L291", "weight": 1.0}, {"source": "laundroapp", "target": "laundroapp_tryapplysession", "relation": "contains", "confidence": "EXTRACTED", "source_file": "components/LaundroApp.tsx", "source_location": "L633", "weight": 1.0}, {"source": "laundroapp", "target": "laundroapp_init", "relation": "contains", "confidence": "EXTRACTED", "source_file": "components/LaundroApp.tsx", "source_location": "L671", "weight": 1.0}, {"source": "laundroapp", "target": "laundroapp_refreshschedule", "relation": "contains", "confidence": "EXTRACTED", "source_file": "components/LaundroApp.tsx", "source_location": "L760", "weight": 1.0}, {"source": "laundroapp", "target": "laundroapp_onfocus", "relation": "contains", "confidence": "EXTRACTED", "source_file": "components/LaundroApp.tsx", "source_location": "L767", "weight": 1.0}, {"source": "laundroapp", "target": "laundroapp_handleobnext", "relation": "contains", "confidence": "EXTRACTED", "source_file": "components/LaundroApp.tsx", "source_location": "L949", "weight": 1.0}, {"source": "laundroapp", "target": "laundroapp_handleobskip", "relation": "contains", "confidence": "EXTRACTED", "source_file": "components/LaundroApp.tsx", "source_location": "L956", "weight": 1.0}, {"source": "laundroapp", "target": "laundroapp_handleloginemail", "relation": "contains", "confidence": "EXTRACTED", "source_file": "components/LaundroApp.tsx", "source_location": "L961", "weight": 1.0}, {"source": "laundroapp", "target": "laundroapp_handlegooglelogin", "relation": "contains", "confidence": "EXTRACTED", "source_file": "components/LaundroApp.tsx", "source_location": "L999", "weight": 1.0}, {"source": "laundroapp", "target": "laundroapp_handleforgotpassword", "relation": "contains", "confidence": "EXTRACTED", "source_file": "components/LaundroApp.tsx", "source_location": "L1008", "weight": 1.0}, {"source": "laundroapp", "target": "laundroapp_handlesetpassword", "relation": "contains", "confidence": "EXTRACTED", "source_file": "components/LaundroApp.tsx", "source_location": "L1030", "weight": 1.0}, {"source": "laundroapp", "target": "laundroapp_handlesavestudentdetailsmodal", "relation": "contains", "confidence": "EXTRACTED", "source_file": "components/LaundroApp.tsx", "source_location": "L1084", "weight": 1.0}, {"source": "laundroapp", "target": "laundroapp_handlesignup", "relation": "contains", "confidence": "EXTRACTED", "source_file": "components/LaundroApp.tsx", "source_location": "L1131", "weight": 1.0}, {"source": "laundroapp", "target": "laundroapp_handlecompleteprofile", "relation": "contains", "confidence": "EXTRACTED", "source_file": "components/LaundroApp.tsx", "source_location": "L1200", "weight": 1.0}, {"source": "laundroapp", "target": "laundroapp_handlesaveeditprofile", "relation": "contains", "confidence": "EXTRACTED", "source_file": "components/LaundroApp.tsx", "source_location": "L1252", "weight": 1.0}, {"source": "laundroapp", "target": "laundroapp_handleselectvendor", "relation": "contains", "confidence": "EXTRACTED", "source_file": "components/LaundroApp.tsx", "source_location": "L1305", "weight": 1.0}, {"source": "laundroapp", "target": "laundroapp_handlescheduleservice", "relation": "contains", "confidence": "EXTRACTED", "source_file": "components/LaundroApp.tsx", "source_location": "L1309", "weight": 1.0}, {"source": "laundroapp", "target": "laundroapp_handlescheduledateslot", "relation": "contains", "confidence": "EXTRACTED", "source_file": "components/LaundroApp.tsx", "source_location": "L1313", "weight": 1.0}, {"source": "laundroapp", "target": "laundroapp_handleconfirmorder", "relation": "contains", "confidence": "EXTRACTED", "source_file": "components/LaundroApp.tsx", "source_location": "L1317", "weight": 1.0}, {"source": "laundroapp", "target": "laundroapp_handleconfirmdelivery", "relation": "contains", "confidence": "EXTRACTED", "source_file": "components/LaundroApp.tsx", "source_location": "L1400", "weight": 1.0}, {"source": "laundroapp", "target": "laundroapp_handlelogout", "relation": "contains", "confidence": "EXTRACTED", "source_file": "components/LaundroApp.tsx", "source_location": "L1420", "weight": 1.0}, {"source": "laundroapp", "target": "laundroapp_handlesetpasswordforemail", "relation": "contains", "confidence": "EXTRACTED", "source_file": "components/LaundroApp.tsx", "source_location": "L1430", "weight": 1.0}, {"source": "laundroapp", "target": "laundroapp_mybillsloading", "relation": "contains", "confidence": "EXTRACTED", "source_file": "components/LaundroApp.tsx", "source_location": "L2447", "weight": 1.0}, {"source": "laundroapp_needsstudenthosteldetails", "target": "laundroapp_iscampuscollegestudent", "relation": "calls", "confidence": "EXTRACTED", "source_file": "components/LaundroApp.tsx", "source_location": "L246", "weight": 1.0}, {"source": "laundroapp_needsstudenthosteldetails", "target": "laundroapp_needsstudentcollegechoice", "relation": "calls", "confidence": "EXTRACTED", "source_file": "components/LaundroApp.tsx", "source_location": "L247", "weight": 1.0}, {"source": "laundroapp_tryapplysession", "target": "laundroapp_rowtouser", "relation": "calls", "confidence": "EXTRACTED", "source_file": "components/LaundroApp.tsx", "source_location": "L641", "weight": 1.0}, {"source": "laundroapp_init", "target": "laundroapp_tryapplysession", "relation": "calls", "confidence": "EXTRACTED", "source_file": "components/LaundroApp.tsx", "source_location": "L683", "weight": 1.0}, {"source": "laundroapp_onfocus", "target": "laundroapp_refreshschedule", "relation": "calls", "confidence": "EXTRACTED", "source_file": "components/LaundroApp.tsx", "source_location": "L767", "weight": 1.0}, {"source": "laundroapp_handleloginemail", "target": "laundroapp_rowtouser", "relation": "calls", "confidence": "EXTRACTED", "source_file": "components/LaundroApp.tsx", "source_location": "L979", "weight": 1.0}, {"source": "laundroapp_handlesetpassword", "target": "laundroapp_rowtouser", "relation": "calls", "confidence": "EXTRACTED", "source_file": "components/LaundroApp.tsx", "source_location": "L1060", "weight": 1.0}, {"source": "laundroapp_handlesavestudentdetailsmodal", "target": "laundroapp_needsstudentcollegechoice", "relation": "calls", "confidence": "EXTRACTED", "source_file": "components/LaundroApp.tsx", "source_location": "L1093", "weight": 1.0}, {"source": "laundroapp_handlesavestudentdetailsmodal", "target": "laundroapp_rowtouser", "relation": "calls", "confidence": "EXTRACTED", "source_file": "components/LaundroApp.tsx", "source_location": "L1117", "weight": 1.0}, {"source": "laundroapp_handlesignup", "target": "laundroapp_validateindianphone", "relation": "calls", "confidence": "EXTRACTED", "source_file": "components/LaundroApp.tsx", "source_location": "L1135", "weight": 1.0}, {"source": "laundroapp_handlesignup", "target": "laundroapp_rowtouser", "relation": "calls", "confidence": "EXTRACTED", "source_file": "components/LaundroApp.tsx", "source_location": "L1180", "weight": 1.0}, {"source": "laundroapp_handlecompleteprofile", "target": "laundroapp_validateindianphone", "relation": "calls", "confidence": "EXTRACTED", "source_file": "components/LaundroApp.tsx", "source_location": "L1204", "weight": 1.0}, {"source": "laundroapp_handlecompleteprofile", "target": "laundroapp_rowtouser", "relation": "calls", "confidence": "EXTRACTED", "source_file": "components/LaundroApp.tsx", "source_location": "L1238", "weight": 1.0}, {"source": "laundroapp_handlesaveeditprofile", "target": "laundroapp_validateindianphone", "relation": "calls", "confidence": "EXTRACTED", "source_file": "components/LaundroApp.tsx", "source_location": "L1256", "weight": 1.0}, {"source": "laundroapp_handlesaveeditprofile", "target": "laundroapp_rowtouser", "relation": "calls", "confidence": "EXTRACTED", "source_file": "components/LaundroApp.tsx", "source_location": "L1291", "weight": 1.0}, {"source": "laundroapp_handleconfirmorder", "target": "laundroapp_needsstudenthosteldetails", "relation": "calls", "confidence": "EXTRACTED", "source_file": "components/LaundroApp.tsx", "source_location": "L1324", "weight": 1.0}, {"source": "laundroapp_handleconfirmorder", "target": "laundroapp_rowtoorder", "relation": "calls", "confidence": "EXTRACTED", "source_file": "components/LaundroApp.tsx", "source_location": "L1386", "weight": 1.0}, {"source": "laundroapp_handleconfirmdelivery", "target": "laundroapp_rowtoorder", "relation": "calls", "confidence": "EXTRACTED", "source_file": "components/LaundroApp.tsx", "source_location": "L1405", "weight": 1.0}]}